embedkit/__init__.py
embedkit/base.py
embedkit/classes.py
embedkit/config.py
embedkit/models.py
embedkit/utils.py
embedkit/providers/__init__.py
embedkit/providers/cohere.py
embedkit/providers/colpali.py
embedkit/providers/jina.py
embedkit/providers/qwen.py
embedkit/providers/snowflake.py
embedkit-0.1.10.dist-info/METADATA
embedkit-0.1.10.dist-info/WHEEL
embedkit-0.1.10.dist-info/licenses/LICENSE
embedkit-0.1.10.dist-info/RECORD
