Metadata-Version: 2.4
Name: embedkit
Version: 0.1.10
Summary: A simple toolkit for generating vector embeddings across multiple providers and models
Author-email: JP Hwang <me@jphwang.com>
License: MIT
License-File: LICENSE
Keywords: ai,cohere,colpali,embeddings,machine-learning,vector
Classifier: Development Status :: 4 - Beta
Classifier: Intended Audience :: Developers
Classifier: License :: OSI Approved :: MIT License
Classifier: Programming Language :: Python :: 3
Classifier: Programming Language :: Python :: 3.10
Classifier: Programming Language :: Python :: 3.11
Classifier: Programming Language :: Python :: 3.12
Classifier: Topic :: Scientific/Engineering :: Artificial Intelligence
Classifier: Topic :: Software Development :: Libraries :: Python Modules
Requires-Python: >=3.10
Requires-Dist: accelerate>=1.7.0
Requires-Dist: cohere>=5.15.0
Requires-Dist: colpali-engine<0.4.0,>=0.3.0
Requires-Dist: pdf2image>=1.17.0
Requires-Dist: pillow>=11.2.1
Requires-Dist: sentence-transformers>=4.1.0
Requires-Dist: torch<=2.5
Requires-Dist: transformers>=4.46.2
